polars_simed-0.3.4.dist-info/METADATA
polars_simed-0.3.4.dist-info/WHEEL
polars_simed-0.3.4.dist-info/licenses/LICENSE.md
polars_simed/__init__.py
polars_simed/_polars_simed_lib.abi3.so
polars_simed/dataframe/__init__.py
polars_simed/dataframe/join.py
polars_simed-0.3.4.dist-info/RECORD
