Metadata-Version: 2.4
Name: polars-simed
Version: 0.3.4
Classifier: Programming Language :: Rust
Classifier: Programming Language :: Python :: Implementation :: CPython
Classifier: Programming Language :: Python :: Implementation :: PyPy
Requires-Dist: polars[pyarrow]>=1.8.2
License-File: LICENSE.md
Summary: Fast similarity join for polars DataFrames. Fork by Edwardvaneechoud with fixes.
Author-email: "Dr. André Schemaitat" <a.schemaitat@gmail.com>, Edwardvaneechoud <evaneechoud@gmail.com>
Requires-Python: >=3.10
